index.py
address_parse-0.0.6.dist-info/LICENSE
address_parse-0.0.6.dist-info/METADATA
address_parse-0.0.6.dist-info/WHEEL
address_parse-0.0.6.dist-info/top_level.txt
address_parse-0.0.6.dist-info/RECORD
